{
  "url": "https://voxday.net/2005/11/07/review-of-right-wing-blogs/",
  "scraped_at": "2026-01-08T20:49:06.925924",
  "title": "A review of right-wing blogs",
  "date_display": "November 7, 2005",
  "date_iso": "2005-11-07T14:17:00+00:00",
  "date_from_url": "2005-11-07",
  "author": "VD",
  "content_html": "<div class=\"entry-content\"><p>This is <a href=\"http://www.qando.net/details.aspx?Entry=2854\">an interesting take</a> on some of the more popular right-leaning blogs.  I’d considering doing my own, except I don’t read enough of them to be able to put together a comprehensive list.  The comments are also entertaining.</p><blockquote><p>(4) Little Green Footballs—Remember that government report that said the “War on Terror” should really be called something like the “War on Islamist Jihadism”? LGF got the memo. All Anti-Islamism, all the time.</p><p>(5) Hugh Hewitt— If you were to combine all three Powerline bloggers, Sean Hannity and any given Republican Party Chairman in some sort of GOP experiment to create the most reliable Republican pundit ever…you’d have Hugh Hewitt: the distilled essence of The Party Man.</p><p>(6) The Volokh Conspiracy—you know how you and your friends used to get into wandering, but interesting, all-night conversations about every subject imaginable—school, politics, jokes, sports, news, girls, philosophy, etc—in your younger days? Replace your old friends with a bunch of libertarian-leaning college professors. It’s the Volokh Conspiracy!</p></blockquote></div>",
  "content_text": "This is\nan interesting take\non some of the more popular right-leaning blogs.  I’d considering doing my own, except I don’t read enough of them to be able to put together a comprehensive list.  The comments are also entertaining.\n(4) Little Green Footballs—Remember that government report that said the “War on Terror” should really be called something like the “War on Islamist Jihadism”? LGF got the memo. All Anti-Islamism, all the time.\n(5) Hugh Hewitt— If you were to combine all three Powerline bloggers, Sean Hannity and any given Republican Party Chairman in some sort of GOP experiment to create the most reliable Republican pundit ever…you’d have Hugh Hewitt: the distilled essence of The Party Man.\n(6) The Volokh Conspiracy—you know how you and your friends used to get into wandering, but interesting, all-night conversations about every subject imaginable—school, politics, jokes, sports, news, girls, philosophy, etc—in your younger days? Replace your old friends with a bunch of libertarian-leaning college professors. It’s the Volokh Conspiracy!",
  "tags": [],
  "categories": [],
  "sitemap_lastmod": "2005-11-07T14:17:00+00:00"
}