{
  "url": "https://voxday.net/2018/07/11/a-captive-of-russia/",
  "scraped_at": "2025-12-19T21:11:10.054737",
  "title": "“A captive of Russia”",
  "date_display": "July 11, 2018",
  "date_iso": "2018-07-11T10:06:26+00:00",
  "date_from_url": "2018-07-11",
  "author": "VD",
  "content_html": "<div class=\"entry-content\"><p>The God-Emperor <a href=\"http://www.dailymail.co.uk/news/article-5941337/Germany-captive-Russia-Trump-dresses-NATOs-secretary-general-Brussels.html\">slams Germany and NATO</a>:</p><blockquote><p>Donald Trump unleashed his fury on NATO Secretary General Jens Stoltenberg on Wednesday for defending Germany’s energy partnership with Russia and threatened Berlin with U.S. action over the deal that he said is wholly inappropriate.</p><p>Trump fumed that ‘Germany is a captive of Russia’ and said the U.S. would ‘have to do something’ in light of the pipeline deal that’s funneling billions into Moscow’s economy.</p><p>‘Germany is totally controlled by Russia,’ he charged. ‘I think its a very bad thing for NATO,’ Trump said.</p><p>Stoltenberg reminded that the U.S. and Europe are ‘stronger together than apart’ and that has been proven by two World Wars and the alliance’s dealings with Russia. Trump told him in response, ‘No, you’re just making Russia richer. You’re not dealing with Russia, you’re making Russia richer.’</p><p>The confrontation stunned the leaders’ senior advisers, including Trump’s secretaries of defense and state. A press aide demanded the media leave the room as Trump pushed Stoltenberg to explain how the U.S. is supposed to protect Germany when it’s opening the front door to Vladimir Putin.</p></blockquote><p>Remember, always wait three days! I’m not certain what the God-Emperor is up to, but I’m confident that the first three media takes on his rhetoric and actions will be wrong. I’m pretty sure he is aware that it is the USA that militarily occupies Germany and not Russia.</p><p>I suspect this is more about trade and cutting US commitments to Europe than anything. After all, if the Germans aren’t going to resist being invaded by millions of migrants, why is the US wasting money to protect them at all?</p><blockquote><p>Trump gave Stoltenberg an earful with media present, telling the visibly startled NATO chief, ‘We’re protecting Germany. We’re protecting France. We’re protecting everybody, and yet, we’re paying a lot of money to protect.’</p><p>Trump said that past presidents did not confront America’s allies because they did not want to meddle in their affairs or they were blind to the problem.</p><p>‘I think that these countries have to step it up — not over a 10-year-period — they have to step it up immediately,’ Trump demanded. ‘Germany is a rich country. They talk about they’re gonna increase it a tiny bit by 2030. Well, they could increase it immediately tomorrow and have no problem.’</p></blockquote></div>",
  "content_text": "The God-Emperor\nslams Germany and NATO\n:\nDonald Trump unleashed his fury on NATO Secretary General Jens Stoltenberg on Wednesday for defending Germany’s energy partnership with Russia and threatened Berlin with U.S. action over the deal that he said is wholly inappropriate.\nTrump fumed that ‘Germany is a captive of Russia’ and said the U.S. would ‘have to do something’ in light of the pipeline deal that’s funneling billions into Moscow’s economy.\n‘Germany is totally controlled by Russia,’ he charged. ‘I think its a very bad thing for NATO,’ Trump said.\nStoltenberg reminded that the U.S. and Europe are ‘stronger together than apart’ and that has been proven by two World Wars and the alliance’s dealings with Russia. Trump told him in response, ‘No, you’re just making Russia richer. You’re not dealing with Russia, you’re making Russia richer.’\nThe confrontation stunned the leaders’ senior advisers, including Trump’s secretaries of defense and state. A press aide demanded the media leave the room as Trump pushed Stoltenberg to explain how the U.S. is supposed to protect Germany when it’s opening the front door to Vladimir Putin.\nRemember, always wait three days! I’m not certain what the God-Emperor is up to, but I’m confident that the first three media takes on his rhetoric and actions will be wrong. I’m pretty sure he is aware that it is the USA that militarily occupies Germany and not Russia.\nI suspect this is more about trade and cutting US commitments to Europe than anything. After all, if the Germans aren’t going to resist being invaded by millions of migrants, why is the US wasting money to protect them at all?\nTrump gave Stoltenberg an earful with media present, telling the visibly startled NATO chief, ‘We’re protecting Germany. We’re protecting France. We’re protecting everybody, and yet, we’re paying a lot of money to protect.’\nTrump said that past presidents did not confront America’s allies because they did not want to meddle in their affairs or they were blind to the problem.\n‘I think that these countries have to step it up — not over a 10-year-period — they have to step it up immediately,’ Trump demanded. ‘Germany is a rich country. They talk about they’re gonna increase it a tiny bit by 2030. Well, they could increase it immediately tomorrow and have no problem.’",
  "tags": [
    "war"
  ],
  "categories": [],
  "sitemap_lastmod": "2018-07-11T09:06:26+00:00"
}