{
  "url": "https://voxday.net/2017/01/31/are-you-tired-ye/",
  "scraped_at": "2025-12-18T06:59:26.587730",
  "title": "Are you tired yet?",
  "date_display": "January 31, 2017",
  "date_iso": "2017-01-31T10:23:00+00:00",
  "date_from_url": "2017-01-31",
  "author": "VD",
  "content_html": "<div class=\"entry-content\"><p>Dark Lord Designs and Cryptofashion have created what can only be described as <a href=\"https://crypto.fashion/products/still-not-tired-of-winning-t-shirt\">a <i>winning </i>new design</a> for sale. And yes, Trumpslide 2020 shirts are on the way. <i>So much winning! </i>It’s a nice way to soft-trigger those who inquire about what sort of winning is involved, at the wearer’s option.</p><div class=\"separator\" style=\"clear: both; text-align: center;\"> <a href=\"https://cdn.shopify.com/s/files/1/1409/4398/products/Winning_Final_1024x1024.png?v=1485652930\" imageanchor=\"1\" style=\"margin-left: 1em; margin-right: 1em;\"><img border=\"0\" decoding=\"async\" fetchpriority=\"high\" height=\"320\" src=\"https://cdn.shopify.com/s/files/1/1409/4398/products/Winning_Final_1024x1024.png?v=1485652930\" width=\"320\"/></a></div></div>",
  "content_text": "Dark Lord Designs and Cryptofashion have created what can only be described as\na\nwinning\nnew design\nfor sale. And yes, Trumpslide 2020 shirts are on the way.\nSo much winning!\nIt’s a nice way to soft-trigger those who inquire about what sort of winning is involved, at the wearer’s option.",
  "tags": [
    "ELoE"
  ],
  "categories": [],
  "sitemap_lastmod": "2017-01-31T10:23:00+00:00"
}