{
  "url": "https://voxday.net/2022/01/18/dont-trust-the-corpocracy/",
  "scraped_at": "2026-01-08T13:06:47.162476",
  "title": "Don’t Trust the Corpocracy",
  "date_display": "January 18, 2022",
  "date_iso": "2022-01-18T00:20:40+00:00",
  "date_from_url": "2022-01-18",
  "author": "VD",
  "content_html": "<div class=\"entry-content\"><p>Building your own platform with the help of the corpocracy is building on <a href=\"https://www.outkick.com/att-succumbs-to-pressure-by-canceling-oan/\">a foundation</a> less stable than sand.</p><blockquote class=\"wp-block-quote is-layout-flow wp-block-quote-is-layout-flow\"><p>AT&amp;T’s DirecTV will drop One America News (OAN) in a move that raises questions about OAN’s future.</p><p>Court findings in October revealed that 90% of OAN’s revenue comes from a contract with AT&amp;T-owned television platforms, including DirecTV. So AT&amp;T, CNN’s parent company, has funded OAN, a pro-Trump news network, almost entirely alone.</p><p>Since the findings, activist groups have pressured AT&amp;T to drop OAN and essentially sink the network’s business model. As we predicted it would at the time, AT&amp;T has willingly succumbed to that pressure.</p><p>“We informed Herring Network, [OAN’s owner], that following a routine internal review, we do not plan to enter into a new contract when our current agreement expires,” a DirecTV spokesperson said Friday.</p><p>Because no other major U.S. cable provider carries OAN, the network’s future as a linear channel is uncertain. As a result, OAN may now have to survive as a direct-to-consumer service.</p><p>While OAN could find a strong enough niche audience to last digitally, the network’s lawyers are not confident it will. In a 2020 court proceeding, an OAN lawyer claimed that “if Herring Networks, for instance, was to lose or not be renewed on DirecTV, the company would go out of business tomorrow.”</p></blockquote><p>If you have a single point of failure, that’s precisely the point that will be targeted by SJWs. You cannot afford to be reliant upon corporations, because corporations have neither principles nor souls. They will not hesitate to betray you and your organization if they see that betrayal as being in their interest.</p><p><a href=\"https://social.infogalactic.com/micropost/a540e986-ef19-4747-bb22-eab4fdbe3a1e\">DISCUSS ON SG</a></p></div>",
  "content_text": "Building your own platform with the help of the corpocracy is building on\na foundation\nless stable than sand.\nAT&T’s DirecTV will drop One America News (OAN) in a move that raises questions about OAN’s future.\nCourt findings in October revealed that 90% of OAN’s revenue comes from a contract with AT&T-owned television platforms, including DirecTV. So AT&T, CNN’s parent company, has funded OAN, a pro-Trump news network, almost entirely alone.\nSince the findings, activist groups have pressured AT&T to drop OAN and essentially sink the network’s business model. As we predicted it would at the time, AT&T has willingly succumbed to that pressure.\n“We informed Herring Network, [OAN’s owner], that following a routine internal review, we do not plan to enter into a new contract when our current agreement expires,” a DirecTV spokesperson said Friday.\nBecause no other major U.S. cable provider carries OAN, the network’s future as a linear channel is uncertain. As a result, OAN may now have to survive as a direct-to-consumer service.\nWhile OAN could find a strong enough niche audience to last digitally, the network’s lawyers are not confident it will. In a 2020 court proceeding, an OAN lawyer claimed that “if Herring Networks, for instance, was to lose or not be renewed on DirecTV, the company would go out of business tomorrow.”\nIf you have a single point of failure, that’s precisely the point that will be targeted by SJWs. You cannot afford to be reliant upon corporations, because corporations have neither principles nor souls. They will not hesitate to betray you and your organization if they see that betrayal as being in their interest.\nDISCUSS ON SG",
  "tags": [
    "corpocracy",
    "media",
    "SJW"
  ],
  "categories": [],
  "sitemap_lastmod": "2022-01-18T00:20:42+00:00"
}